CHANGELOG.rst
LICENSE
MANIFEST.in
README.rst
setup.py
gipc/__init__.py
gipc/gipc.py
gipc.egg-info/PKG-INFO
gipc.egg-info/SOURCES.txt
gipc.egg-info/dependency_links.txt
gipc.egg-info/requires.txt
gipc.egg-info/top_level.txt
test/test_gipc.py