Metadata-Version: 2.4
Name: gipc
Version: 1.8.0
Summary: gevent-cooperative child processes and inter-process communication.
Home-page: https://gehrcke.de/gipc
Author: Dr. Jan-Philip Gehrcke
Author-email: jgehrcke@googlemail.com
Keywords: gevent,multiprocessing,ipc,child processes
Platform: POSIX
Platform: Windows
Classifier: License :: OSI Approved :: MIT License
Classifier: Programming Language :: Python
Classifier: Programming Language :: Python :: 3.9
Classifier: Programming Language :: Python :: 3.10
Classifier: Programming Language :: Python :: 3.11
Classifier: Programming Language :: Python :: 3.12
Classifier: Programming Language :: Python :: 3.13
Classifier: Programming Language :: Python :: Implementation :: CPython
Classifier: Programming Language :: Python :: Implementation :: PyPy
Classifier: Operating System :: MacOS :: MacOS X
Classifier: Operating System :: POSIX
Classifier: Operating System :: Microsoft :: Windows
Classifier: Topic :: Software Development :: Libraries :: Python Modules
Classifier: Topic :: System :: Hardware :: Symmetric Multi-processing
Classifier: Intended Audience :: Developers
License-File: LICENSE
Requires-Dist: gevent>=1.5
Dynamic: author
Dynamic: author-email
Dynamic: classifier
Dynamic: description
Dynamic: description-content-type
Dynamic: home-page
Dynamic: keywords
Dynamic: license-file
Dynamic: platform
Dynamic: requires-dist
Dynamic: summary
